{"title":"Beumer Utrecht","url":"https://www.beumer.nl/wonen/zoeken/heel-nederland/0-700000/utrecht/100-oppervlakte/3-slaapkamers/beschikbaar/","favicon":"https://www.beumer.nl/app/uploads/2021/11/cropped-favicon-150x150.png","elements":[{"title":"Sweder van Zuylenweg 15","contents":"<a href=\"https://www.beumer.nl/wonen/object/sweder-van-zuylenweg-15-utrecht/\" class=\"card-house\">\n    <div class=\"offer\">\n        <div class=\"card-house__thumb\">\n\n                                                <picture class=\"background\">\n                        <source media=\"(min-width:1024px)\" data-srcset=\"/app/uploads/sure/media/MA12860/MA12860-203213-Sweder-van-Zuylenweg-15-Utrecht-221236259-600x476-c-default.webp\" srcset=\"/app/uploads/sure/media/MA12860/MA12860-203213-Sweder-van-Zuylenweg-15-Utrecht-221236259-600x476-c-default.webp\">\n                        <source media=\"(min-width:100px)\" data-srcset=\"/app/uploads/sure/media/MA12860/MA12860-203213-Sweder-van-Zuylenweg-15-Utrecht-221236259-400x317-c-default.webp\" srcset=\"/app/uploads/sure/media/MA12860/MA12860-203213-Sweder-van-Zuylenweg-15-Utrecht-221236259-400x317-c-default.webp\">\n                        <img loading=\"lazy\" data-src=\"/app/uploads/sure/media/MA12860/MA12860-203213-Sweder-van-Zuylenweg-15-Utrecht-221236259-150x150.jpg\" alt=\"                        Sweder van Zuylenweg 15\n                    \" src=\"/app/uploads/sure/media/MA12860/MA12860-203213-Sweder-van-Zuylenweg-15-Utrecht-221236259-150x150.jpg\" data-ll-status=\"loaded\" class=\"loaded\">\n                    </picture>\n                            \n                        <div class=\"card-house__label__holder\">\n                                                                                        <div class=\"card-house__label\">Beschikbaar</div>\n                                                            \n                            </div>\n        </div>\n        <div class=\"card-house__content\">\n            <h3>\n                                    Sweder van Zuylenweg 15\n                            </h3>\n\n            <p>\n                                                    Utrecht •\n                                                                            € 595.000\n                        ,- k.k.\n                                                </p>\n\n            <div class=\"card-house__content__data\">\n                                    <p>\n                        <i class=\"icon icon-house\"></i>\n                        <span>146 m<sup>2</sup></span>\n                    </p>\n                                                    <p>\n                        <i class=\"icon icon-doorstep\"></i>\n                        5 kamer(s)\n                    </p>\n                                                    <p>\n                        <i class=\"icon icon-label\"></i>\n                        C\n                    </p>\n                            </div>\n        </div>\n    </div>\n</a>","link":"https://www.beumer.nl/wonen/object/sweder-van-zuylenweg-15-utrecht/","retrieved":1742492719100},{"title":"Augusto Sandinostraat 33","contents":"<a href=\"https://www.beumer.nl/wonen/object/augusto-sandinostraat-33-utrecht/\" class=\"card-house\">\n    <div class=\"offer\">\n        <div class=\"card-house__thumb\">\n\n                                                <picture class=\"background\">\n                        <source media=\"(min-width:1024px)\" data-srcset=\"/app/uploads/sure/media/UT102552/UT102552-202771-Augusto-Sandinostraat-33-Utrecht-221231315-600x476-c-default.webp\" srcset=\"/app/uploads/sure/media/UT102552/UT102552-202771-Augusto-Sandinostraat-33-Utrecht-221231315-600x476-c-default.webp\">\n                        <source media=\"(min-width:100px)\" data-srcset=\"/app/uploads/sure/media/UT102552/UT102552-202771-Augusto-Sandinostraat-33-Utrecht-221231315-400x317-c-default.webp\" srcset=\"/app/uploads/sure/media/UT102552/UT102552-202771-Augusto-Sandinostraat-33-Utrecht-221231315-400x317-c-default.webp\">\n                        <img loading=\"lazy\" data-src=\"/app/uploads/sure/media/UT102552/UT102552-202771-Augusto-Sandinostraat-33-Utrecht-221231315-150x150.jpg\" alt=\"                        Augusto Sandinostraat 33\n                    \" src=\"/app/uploads/sure/media/UT102552/UT102552-202771-Augusto-Sandinostraat-33-Utrecht-221231315-150x150.jpg\" data-ll-status=\"loaded\" class=\"loaded\">\n                    </picture>\n                            \n                        <div class=\"card-house__label__holder\">\n                                                                                        <div class=\"card-house__label\">Beschikbaar</div>\n                                                            \n                            </div>\n        </div>\n        <div class=\"card-house__content\">\n            <h3>\n                                    Augusto Sandinostraat 33\n                            </h3>\n\n            <p>\n                                                    Utrecht •\n                                                                            € 575.000\n                        ,- k.k.\n                                                </p>\n\n            <div class=\"card-house__content__data\">\n                                    <p>\n                        <i class=\"icon icon-house\"></i>\n                        <span>106 m<sup>2</sup></span>\n                    </p>\n                                                    <p>\n                        <i class=\"icon icon-doorstep\"></i>\n                        5 kamer(s)\n                    </p>\n                                                    <p>\n                        <i class=\"icon icon-label\"></i>\n                        A\n                    </p>\n                            </div>\n        </div>\n    </div>\n</a>","link":"https://www.beumer.nl/wonen/object/augusto-sandinostraat-33-utrecht/","retrieved":1742320104703},{"title":"Ondiep 103","contents":"<a href=\"https://www.beumer.nl/wonen/object/ondiep-103-utrecht/\" class=\"card-house\">\n    <div class=\"offer\">\n        <div class=\"card-house__thumb\">\n\n                                                <picture class=\"background\">\n                        <source media=\"(min-width:1024px)\" data-srcset=\"/app/uploads/sure/media/UT102880/UT102880-202487-Ondiep-103-Utrecht-219931225-600x476-c-default.webp\" srcset=\"/app/uploads/sure/media/UT102880/UT102880-202487-Ondiep-103-Utrecht-219931225-600x476-c-default.webp\">\n                        <source media=\"(min-width:100px)\" data-srcset=\"/app/uploads/sure/media/UT102880/UT102880-202487-Ondiep-103-Utrecht-219931225-400x317-c-default.webp\" srcset=\"/app/uploads/sure/media/UT102880/UT102880-202487-Ondiep-103-Utrecht-219931225-400x317-c-default.webp\">\n                        <img loading=\"lazy\" data-src=\"/app/uploads/sure/media/UT102880/UT102880-202487-Ondiep-103-Utrecht-219931225-150x150.jpg\" alt=\"                        Ondiep 103\n                    \" src=\"/app/uploads/sure/media/UT102880/UT102880-202487-Ondiep-103-Utrecht-219931225-150x150.jpg\" data-ll-status=\"loaded\" class=\"loaded\">\n                    </picture>\n                            \n                        <div class=\"card-house__label__holder\">\n                                                                                        <div class=\"card-house__label\">Beschikbaar</div>\n                                                            \n                            </div>\n        </div>\n        <div class=\"card-house__content\">\n            <h3>\n                                    Ondiep 103\n                            </h3>\n\n            <p>\n                                                    Utrecht •\n                                                                            € 625.000\n                        ,- k.k.\n                                                </p>\n\n            <div class=\"card-house__content__data\">\n                                    <p>\n                        <i class=\"icon icon-house\"></i>\n                        <span>120 m<sup>2</sup></span>\n                    </p>\n                                                    <p>\n                        <i class=\"icon icon-doorstep\"></i>\n                        5 kamer(s)\n                    </p>\n                                                    <p>\n                        <i class=\"icon icon-label\"></i>\n                        A+\n                    </p>\n                            </div>\n        </div>\n    </div>\n</a>","link":"https://www.beumer.nl/wonen/object/ondiep-103-utrecht/","retrieved":1742233147847},{"title":"Koppestokstraat 78","contents":"<a href=\"https://www.beumer.nl/wonen/object/koppestokstraat-78-utrecht/\" class=\"card-house\">\n    <div class=\"offer\">\n        <div class=\"card-house__thumb\">\n\n                                                <picture class=\"background\">\n                        <source media=\"(min-width:1024px)\" data-srcset=\"/app/uploads/sure/media/UT102869/UT102869-201602-Koppestokstraat-78-Utrecht-220089741-600x476-c-default.webp\" srcset=\"/app/uploads/sure/media/UT102869/UT102869-201602-Koppestokstraat-78-Utrecht-220089741-600x476-c-default.webp\">\n                        <source media=\"(min-width:100px)\" data-srcset=\"/app/uploads/sure/media/UT102869/UT102869-201602-Koppestokstraat-78-Utrecht-220089741-400x317-c-default.webp\" srcset=\"/app/uploads/sure/media/UT102869/UT102869-201602-Koppestokstraat-78-Utrecht-220089741-400x317-c-default.webp\">\n                        <img loading=\"lazy\" data-src=\"/app/uploads/sure/media/UT102869/UT102869-201602-Koppestokstraat-78-Utrecht-220089741-150x150.jpg\" alt=\"                        Koppestokstraat 78\n                    \" src=\"/app/uploads/sure/media/UT102869/UT102869-201602-Koppestokstraat-78-Utrecht-220089741-150x150.jpg\" data-ll-status=\"loaded\" class=\"loaded\">\n                    </picture>\n                            \n                        <div class=\"card-house__label__holder\">\n                                                                                        <div class=\"card-house__label\">Beschikbaar</div>\n                                                            \n                            </div>\n        </div>\n        <div class=\"card-house__content\">\n            <h3>\n                                    Koppestokstraat 78\n                            </h3>\n\n            <p>\n                                                    Utrecht •\n                                                                            € 539.000\n                        ,- k.k.\n                                                </p>\n\n            <div class=\"card-house__content__data\">\n                                    <p>\n                        <i class=\"icon icon-house\"></i>\n                        <span>107 m<sup>2</sup></span>\n                    </p>\n                                                    <p>\n                        <i class=\"icon icon-doorstep\"></i>\n                        5 kamer(s)\n                    </p>\n                                                    <p>\n                        <i class=\"icon icon-label\"></i>\n                        B\n                    </p>\n                            </div>\n        </div>\n    </div>\n</a>","link":"https://www.beumer.nl/wonen/object/koppestokstraat-78-utrecht/","retrieved":1741715098126}]}