{"title":"Domvast","url":"https://domvast.nl/woningen/#q1YqyElMLClWslIqLSlKTc4oUdJRKi5JLCkFCkUrJaUWJ2dkZiclJhYpxeoo5RelpBYlVQIVQ5RYJRYnK9UCAA","favicon":"https://domvast.nl/wp-content/uploads/2023/09/cropped-favicon-32x32.png","elements":[{"title":"Amsterdamsestraatweg 568","contents":"<div class=\"item\">\n\t\t<p class=\"status-indicator\"><span class=\"Beschikbaar\">Beschikbaar</span></p>\n\t\t<a href=\"https://domvast.nl/woning/utrecht-amsterdamsestraatweg-568/\" class=\"thumbnail\">\n           <img width=\"300\" height=\"200\" src=\"https://domvast.nl/wp-content/uploads/realworks/wonen/9.182.614/233514912-300x200.jpg\" class=\"attachment-medium size-medium wp-post-image\" alt=\"\" decoding=\"async\" loading=\"lazy\">\t\t</a>\n\t\t<div class=\"item-content\">\n\t\t\t<header>\n\t\t\t\t<h2>UTRECHT</h2>\n\t\t\t\t<h2>Amsterdamsestraatweg 568</h2>\n\t\t\t</header>\n\t\t\t<div class=\"entry-content\">\n\t\t\t\t\t\t\t\n\n\t\t\t\t<dl><dt>Koopprijs</dt><dd>€ 550.000,- k.k.</dd><dt>Woonopp.</dt><dd>92 m<sup>2</sup></dd><dt>Aantal slaapkamers</dt><dd>2</dd></dl>\t\t\t</div>\n\t\t</div>\n\t\t<a href=\"https://domvast.nl/woning/utrecht-amsterdamsestraatweg-568/\" class=\"overlay\" rel=\"bookmark\"></a>\n\t</div>","link":"https://domvast.nl/woning/utrecht-amsterdamsestraatweg-568/","retrieved":1749664542459}]}