{"title":"Makelaarsland","url":"https://www.makelaarsland.nl/huis-kopen/?_q=Utrecht&min=&max=700000&type=&kamers=4","favicon":"https://www.makelaarsland.nl/content/themes/makelaarsland/assets/favicon/favicon-32x32.png","elements":[{"title":"Knopstraat 31\n            Utrecht\n            5 kamers\n          \n          \n            € 695.000","contents":"<figure class=\"m-search-result__slider-wrap\">\n  <button class=\"m-search-result__button hidden\" data-previous-slide=\"previous\"></button>\n  <a href=\"https://www.makelaarsland.nl/huis-kopen/utrecht-knopstraat-31-2/\">\n    <div class=\"m-search-result-slider\" data-slider-container=\"\" style=\"width: 1860px;\">\n\n      \n        \n        \n        <div data-image-src=\"https://media.nvm.nl/512x/94204f85-0fa0-407d-861a-7d001f32e9ca\" class=\"m-search-result__image\" data-index=\"0\" style=\"width: 372px; background-image: url(&quot;https://media.nvm.nl/512x/94204f85-0fa0-407d-861a-7d001f32e9ca&quot;); opacity: 1;\" data-is-in-view=\"true\"></div>\n\n      \n        \n        \n        <div data-image-src=\"https://media.nvm.nl/512x/c7d1eda7-92ec-40f2-b9b7-c2cf3ba38b4d\" class=\"m-search-result__image\" data-index=\"1\" style=\"width: 372px;\"></div>\n\n      \n        \n        \n        <div data-image-src=\"https://media.nvm.nl/512x/120d4122-1ef2-451d-bd59-b88fa10d77e0\" class=\"m-search-result__image\" data-index=\"2\" style=\"width: 372px;\"></div>\n\n      \n        \n        \n        <div data-image-src=\"https://media.nvm.nl/512x/06b7c782-4a1e-411c-8aa9-097408166017\" class=\"m-search-result__image\" data-index=\"3\" style=\"width: 372px;\"></div>\n\n      \n        \n        \n        <div data-image-src=\"https://media.nvm.nl/512x/a89b6968-ea10-44e5-bd83-1611fa618d9e\" class=\"m-search-result__image\" data-index=\"4\" style=\"width: 372px;\"></div>\n\n      \n    </div>\n  </a>\n  <button class=\"m-search-result__button\" data-next-slide=\"next\"></button>\n</figure>\n\n        <a href=\"https://www.makelaarsland.nl/huis-kopen/utrecht-knopstraat-31-2/\" class=\"m-search-result__content-wrap\">\n          <div class=\"m-search-result__content\">\n            <h3 class=\"m-search-result__adress\">Knopstraat 31</h3>\n            <h3 class=\"m-search-result__city\">Utrecht</h3>\n            <h4 class=\"m-search-result__amount-of-rooms\">5 kamers</h4>\n          </div>\n          <div class=\"m-search-result__details\">\n            <h3 class=\"m-search-result__price\"><span>€</span> 695.000</h3>\n\n            <div class=\"m-search-result__status-wrap\">\n              \n                          </div>\n\n          </div>\n        </a>","link":"https://www.makelaarsland.nl/huis-kopen/utrecht-knopstraat-31-2/","retrieved":1751132424205},{"title":"Melissekade 221\n            Utrecht\n            4 kamers\n          \n          \n            € 475.000","contents":"<figure class=\"m-search-result__slider-wrap\">\n  <button class=\"m-search-result__button hidden\" data-previous-slide=\"previous\"></button>\n  <a href=\"https://www.makelaarsland.nl/huis-kopen/utrecht-melissekade-221/\">\n    <div class=\"m-search-result-slider\" data-slider-container=\"\" style=\"width: 1860px;\">\n\n      \n        \n        \n        <div data-image-src=\"https://media.nvm.nl/512x/d92b628c-82e6-4d6a-b60e-13f6c518cd8e\" class=\"m-search-result__image\" data-index=\"0\" style=\"width: 372px; background-image: url(&quot;https://media.nvm.nl/512x/d92b628c-82e6-4d6a-b60e-13f6c518cd8e&quot;); opacity: 1;\" data-is-in-view=\"true\"></div>\n\n      \n        \n        \n        <div data-image-src=\"https://media.nvm.nl/512x/625e8423-e935-40a4-8fe6-c7fe2a0bd5a8\" class=\"m-search-result__image\" data-index=\"1\" style=\"width: 372px;\"></div>\n\n      \n        \n        \n        <div data-image-src=\"https://media.nvm.nl/512x/7bf39395-8c78-48aa-90eb-4a28c5faa86b\" class=\"m-search-result__image\" data-index=\"2\" style=\"width: 372px;\"></div>\n\n      \n        \n        \n        <div data-image-src=\"https://media.nvm.nl/512x/c8a8fa91-d940-4f1c-a625-10263b0c00d1\" class=\"m-search-result__image\" data-index=\"3\" style=\"width: 372px;\"></div>\n\n      \n        \n        \n        <div data-image-src=\"https://media.nvm.nl/512x/b446397d-1209-43ff-ae9b-ad2f5cbf9bb8\" class=\"m-search-result__image\" data-index=\"4\" style=\"width: 372px;\"></div>\n\n      \n    </div>\n  </a>\n  <button class=\"m-search-result__button\" data-next-slide=\"next\"></button>\n</figure>\n\n        <a href=\"https://www.makelaarsland.nl/huis-kopen/utrecht-melissekade-221/\" class=\"m-search-result__content-wrap\">\n          <div class=\"m-search-result__content\">\n            <h3 class=\"m-search-result__adress\">Melissekade 221</h3>\n            <h3 class=\"m-search-result__city\">Utrecht</h3>\n            <h4 class=\"m-search-result__amount-of-rooms\">4 kamers</h4>\n          </div>\n          <div class=\"m-search-result__details\">\n            <h3 class=\"m-search-result__price\"><span>€</span> 475.000</h3>\n\n            <div class=\"m-search-result__status-wrap\">\n              \n                          </div>\n\n          </div>\n        </a>","link":"https://www.makelaarsland.nl/huis-kopen/utrecht-melissekade-221/","retrieved":1751046583232},{"contents":"<div class=\"m-search-result-nvm\">\n    <div class=\"m-search-result-nvm__content\">\n\n       \n\n      <h3 class=\"e-title e-title--secondary\">Bekijk <strong>381 woningen</strong> in het complete NVM aanbod.</h3>\n\n      <a id=\"nvm-dynamic-link\" href=\"https://mijn.makelaarsland.nl/aanbod/zoeken/?zoekterm=Utrecht&amp;minimum=&amp;maximum=700000&amp;huistype=&amp;aantalkamers=4\" data-href=\"https://mijn.makelaarsland.nl/aanbod/zoeken/\" class=\"e-btn e-btn--simple\" target=\"_blank\">Bekijk alle woningen</a>\n\n    </div>\n  </div>","retrieved":1751953640052}]}